kancyer.py
kancyer-0.0.7.dist-info/METADATA
kancyer-0.0.7.dist-info/WHEEL
kancyer-0.0.7.dist-info/entry_points.txt
kancyer-0.0.7.dist-info/top_level.txt
kancyer-0.0.7.dist-info/RECORD
