Metadata-Version: 2.1
Name: kancyer
Version: 0.0.7
Summary: 一个常用的工具集。
Home-page: https://github.com/kancyframework/python-plugins/tree/main/kancyer
Author: kancy
Author-email: 793272861@qq.com
License: MIT
Platform: UNKNOWN
Classifier: License :: OSI Approved :: MIT License
Classifier: Programming Language :: Python
Classifier: Programming Language :: Python :: 3
Classifier: Programming Language :: Python :: 3.6
Classifier: Programming Language :: Python :: Implementation :: CPython
Classifier: Programming Language :: Python :: Implementation :: PyPy
Requires-Python: >=3
Requires-Dist: kancylog
Requires-Dist: fileer
Requires-Dist: randomer
Requires-Dist: langeer
Requires-Dist: timeer
Requires-Dist: sfer
Requires-Dist: objectjson
Provides-Extra: aes_feature
Requires-Dist: pycryptodomex ; extra == 'aes_feature'
